oralb/__init__.py
oralb-0.2.dist-info/LICENSE.txt
oralb-0.2.dist-info/METADATA
oralb-0.2.dist-info/WHEEL
oralb-0.2.dist-info/top_level.txt
oralb-0.2.dist-info/RECORD
