Metadata-Version: 2.1
Name: oralb
Version: 0.2
Summary: Connect to an OralB toothbrush via Bluetooth
Home-page: https://github.com/bkbilly/oralb
Author: bkbilly
Author-email: bkbilly@hotmail.com
License: UNKNOWN
Platform: UNKNOWN
Classifier: Programming Language :: Python :: 3.9
Classifier: License :: OSI Approved :: MIT License
Classifier: Operating System :: OS Independent
Requires-Dist: bleak (>=0.18.1bleak-retry-connector>=2.1.3)
